{
	"configurations" : 
	[
		{
			"directories" : 
			[
				{
					"build" : ".",
					"jsonFile" : "directory-.-Debug-d0094a50bb2071803777.json",
					"minimumCMakeVersion" : 
					{
						"string" : "3.26"
					},
					"projectIndex" : 0,
					"source" : ".",
					"targetIndexes" : 
					[
						0
					]
				}
			],
			"name" : "Debug",
			"projects" : 
			[
				{
					"directoryIndexes" : 
					[
						0
					],
					"name" : "Assignment1_initial",
					"targetIndexes" : 
					[
						0
					]
				}
			],
			"targets" : 
			[
				{
					"directoryIndex" : 0,
					"id" : "Assignment1_initial::@6890427a1f51a3e7e1df",
					"jsonFile" : "target-Assignment1_initial-Debug-41ec01544a798d8a82ea.json",
					"name" : "Assignment1_initial",
					"projectIndex" : 0
				}
			]
		}
	],
	"kind" : "codemodel",
	"paths" : 
	{
		"build" : "C:/Users/jacop/Uni Drive/Ing Matematica-2.0/ALGORITHMS AND PARALLEL COMPUTING/Assignments/Assignments2023/Assignment1/10687726/cmake-build-debug",
		"source" : "C:/Users/jacop/Uni Drive/Ing Matematica-2.0/ALGORITHMS AND PARALLEL COMPUTING/Assignments/Assignments2023/Assignment1/10687726"
	},
	"version" : 
	{
		"major" : 2,
		"minor" : 5
	}
}
